yarg/__about__.py
yarg/__init__.py
yarg/client.py
yarg/exceptions.py
yarg/package.py
yarg/parse.py
yarg/release.py
yarg-0.1.10.dist-info/LICENSE
yarg-0.1.10.dist-info/LICENSE-REQUESTS
yarg-0.1.10.dist-info/METADATA
yarg-0.1.10.dist-info/WHEEL
yarg-0.1.10.dist-info/top_level.txt
yarg-0.1.10.dist-info/zip-safe
yarg-0.1.10.dist-info/RECORD
