Metadata-Version: 2.1
Name: yarg
Version: 0.1.10
Summary: A semi hard Cornish cheese, also queries PyPI (PyPI client)
Home-page: https://yarg.readthedocs.org/
Author: Kura
Author-email: kura@kura.io
Maintainer: Kura
Maintainer-email: kura@kura.io
License: MIT
Keywords: pypi,client,packages
Platform: linux
Classifier: Development Status :: 4 - Beta
Classifier: Intended Audience :: Developers
Classifier: Natural Language :: English
Classifier: License :: OSI Approved :: MIT License
Classifier: Programming Language :: Python
Classifier: Programming Language :: Python :: 3
Classifier: Programming Language :: Python :: 3.8
Classifier: Programming Language :: Python :: 3.9
Classifier: Programming Language :: Python :: 3.10
Classifier: Programming Language :: Python :: 3.11
Classifier: Programming Language :: Python :: 3.12
Classifier: Programming Language :: Python :: Implementation :: CPython
Classifier: Programming Language :: Python :: Implementation :: PyPy
Classifier: Topic :: Software Development :: Libraries :: Python Modules
Classifier: Topic :: System :: Archiving :: Packaging
Requires: requests
Provides: yarg
License-File: LICENSE
License-File: LICENSE-REQUESTS
